README.md
setup.py
misp/__init__.py
misp/_version.py
misp/transforms.py
misp.egg-info/PKG-INFO
misp.egg-info/SOURCES.txt
misp.egg-info/dependency_links.txt
misp.egg-info/not-zip-safe
misp.egg-info/requires.txt
misp.egg-info/top_level.txt
misp/models/__init__.py
misp/models/cbamresnet.py
misp/models/tailnet.py
misp/models/tailunet.py
misp/models/efficientunet/__init__.py
misp/models/efficientunet/efficientnet.py
misp/models/efficientunet/layers.py
misp/models/efficientunet/tailefficientunet.py
misp/models/efficientunet/utils.py
misp/utils/__init__.py
misp/utils/file_utils.py
misp/utils/utils.py
misp/utils/visual_utils.py
misp/utils/wsi_utils.py