Metadata-Version: 1.2
Name: misp
Version: 0.1.5
Summary: Medical Image Segmentation Pipeline
Home-page: https://github.com/zhoudaxia233/misp
License: MIT
Platform: UNKNOWN
Requires-Python: >=3.6
